large_image_source_dicom/__init__.py
large_image_source_dicom/dicom_metadata.py
large_image_source_dicom/dicom_tags.py
large_image_source_dicom/dicomweb_utils.py
large_image_source_dicom/girder_plugin.py
large_image_source_dicom/girder_source.py
large_image_source_dicom/assetstore/__init__.py
large_image_source_dicom/assetstore/dicomweb_assetstore_adapter.py
large_image_source_dicom/assetstore/rest.py
large_image_source_dicom/web_client/constants.js
large_image_source_dicom/web_client/main.js
large_image_source_dicom/web_client/package.json
large_image_source_dicom/web_client/templates/assetstoreImport.pug
large_image_source_dicom/web_client/templates/dicomwebAssetstoreCreate.pug
large_image_source_dicom/web_client/templates/dicomwebAssetstoreEditFields.pug
large_image_source_dicom/web_client/templates/dicomwebAssetstoreImportButton.pug
large_image_source_dicom/web_client/templates/dicomwebAssetstoreMixins.pug
large_image_source_dicom/web_client/views/AssetstoresView.js
large_image_source_dicom/web_client/views/AuthOptions.js
large_image_source_dicom/web_client/views/DICOMwebImportView.js
large_image_source_dicom/web_client/views/EditAssetstoreWidget.js
large_image_source_dicom/web_client/views/NewAssetstoreWidget.js
large_image_source_dicom-1.34.0.dist-info/licenses/LICENSE
large_image_source_dicom-1.34.0.dist-info/METADATA
large_image_source_dicom-1.34.0.dist-info/WHEEL
large_image_source_dicom-1.34.0.dist-info/entry_points.txt
large_image_source_dicom-1.34.0.dist-info/top_level.txt
large_image_source_dicom-1.34.0.dist-info/RECORD
