Metadata-Version: 2.4
Name: large-image-source-dicom
Version: 1.34.0
Summary: A DICOM tilesource for large_image.
Home-page: https://github.com/girder/large_image
Author: Kitware, Inc.
Author-email: kitware@kitware.com
License: Apache-2.0
Keywords: large_image,tile source
Classifier: Development Status :: 5 - Production/Stable
Classifier: Programming Language :: Python :: 3
Classifier: Programming Language :: Python :: 3.10
Classifier: Programming Language :: Python :: 3.11
Classifier: Programming Language :: Python :: 3.12
Classifier: Programming Language :: Python :: 3.13
Classifier: Programming Language :: Python :: 3.14
Requires-Python: >=3.10
License-File: LICENSE
Requires-Dist: large-image>=1.34.0
Requires-Dist: wsidicom!=0.21.3,>=0.9.0
Requires-Dist: pydicom<3; python_version < "3.10"
Requires-Dist: pydicom; python_version >= "3.10"
Provides-Extra: girder
Requires-Dist: girder-large-image>=1.34.0; extra == "girder"
Requires-Dist: girder>=3.2.3; extra == "girder"
Dynamic: author
Dynamic: author-email
Dynamic: classifier
Dynamic: description
Dynamic: description-content-type
Dynamic: home-page
Dynamic: keywords
Dynamic: license
Dynamic: license-file
Dynamic: provides-extra
Dynamic: requires-dist
Dynamic: requires-python
Dynamic: summary
